gexp/__init__.py
gexp/cli.py
gexp-1.0.1.dist-info/LICENSE
gexp-1.0.1.dist-info/METADATA
gexp-1.0.1.dist-info/WHEEL
gexp-1.0.1.dist-info/entry_points.txt
gexp-1.0.1.dist-info/top_level.txt
gexp-1.0.1.dist-info/RECORD
