Metadata-Version: 2.2
Name: gexp
Version: 1.0.1
Summary: A simple CLI to export whole directories into a single string with .gitignore support and more.
Author-email: Gusarich <gusarich@icloud.com>
License: MIT License
Project-URL: Homepage, https://github.com/Gusarich/gexp
Project-URL: Issues, https://github.com/Gusarich/gexp/issues
Keywords: export,files,gitignore,cli
Classifier: Programming Language :: Python :: 3
Classifier: License :: OSI Approved :: MIT License
Classifier: Operating System :: OS Independent
License-File: LICENSE
Requires-Dist: pathspec>=0.9.0
